Flask_Cache_Cassandra-0.14.6.dist-info/DESCRIPTION.rst
Flask_Cache_Cassandra-0.14.6.dist-info/METADATA
Flask_Cache_Cassandra-0.14.6.dist-info/RECORD
Flask_Cache_Cassandra-0.14.6.dist-info/WHEEL
Flask_Cache_Cassandra-0.14.6.dist-info/metadata.json
Flask_Cache_Cassandra-0.14.6.dist-info/top_level.txt
flask_cache/__init__.py
flask_cache/_compat.py
flask_cache/backends.py
flask_cache/jinja2ext.py
