Metadata-Version: 2.0
Name: Flask-Cache-Cassandra
Version: 0.14.6
Summary: Adds cache support to your Flask application
Home-page: http://github.com/a-tal/flask-cache-cassandra
Author: Adam Talsma
Author-email: adam@talsma.ca
License: BSD
Platform: any
Classifier: Development Status :: 4 - Beta
Classifier: Environment :: Web Environment
Classifier: Intended Audience :: Developers
Classifier: License :: OSI Approved :: BSD License
Classifier: Operating System :: OS Independent
Classifier: Programming Language :: Python
Classifier: Programming Language :: Python :: 2
Classifier: Programming Language :: Python :: 2.6
Classifier: Programming Language :: Python :: 2.7
Classifier: Programming Language :: Python :: 3
Classifier: Programming Language :: Python :: 3.3
Classifier: Topic :: Internet :: WWW/HTTP :: Dynamic Content
Classifier: Topic :: Software Development :: Libraries :: Python Modules
Provides: flask_cache
Obsoletes: flask_cache
Requires-Dist: Flask
